--- jar:file:///Users/olegstotsky/Desktop/Code/JBSpring2020/dist-compare/compare/dist_gradle/artifacts/ideaPlugin/Kotlin/kotlinc/lib/android-extensions-compiler.jar!/org/jetbrains/kotlin/android/synthetic/AndroidConstKt.class
+++ jar:file:///Users/olegstotsky/Desktop/Code/JBSpring2020/dist-compare/compare/dist_jps/artifacts/ideaPlugin/Kotlin/kotlinc/lib/android-extensions-compiler.jar!/org/jetbrains/kotlin/android/synthetic/AndroidConstKt.class
@@ -50,24 +50,24 @@
    #44 = Utf8               (I)Ljava/lang/Object;
    #45 = NameAndType        #43:#44       // get:(I)Ljava/lang/Object;
    #46 = InterfaceMethodref #42.#45       // java/util/List.get:(I)Ljava/lang/Object;
    #47 = Utf8               java/lang/String
    #48 = Class              #47           // java/lang/String
-   #49 = Utf8               getJavaIdentifierNameForResourceName
-   #50 = Utf8               (Ljava/lang/String;)Ljava/lang/String;
-   #51 = NameAndType        #49:#50       // getJavaIdentifierNameForResourceName:(Ljava/lang/String;)Ljava/lang/String;
-   #52 = Methodref          #2.#51        // org/jetbrains/kotlin/android/synthetic/AndroidConstKt.getJavaIdentifierNameForResourceName:(Ljava/lang/String;)Ljava/lang/String;
-   #53 = Utf8               length
-   #54 = Utf8               ()I
-   #55 = NameAndType        #53:#54       // length:()I
-   #56 = InterfaceMethodref #28.#55       // java/lang/CharSequence.length:()I
-   #57 = Utf8               org/jetbrains/kotlin/android/synthetic/res/ResourceIdentifier
-   #58 = Class              #57           // org/jetbrains/kotlin/android/synthetic/res/ResourceIdentifier
+   #49 = Utf8               org/jetbrains/kotlin/android/synthetic/res/ResourceIdentifier
+   #50 = Class              #49           // org/jetbrains/kotlin/android/synthetic/res/ResourceIdentifier
+   #51 = Utf8               getJavaIdentifierNameForResourceName
+   #52 = Utf8               (Ljava/lang/String;)Ljava/lang/String;
+   #53 = NameAndType        #51:#52       // getJavaIdentifierNameForResourceName:(Ljava/lang/String;)Ljava/lang/String;
+   #54 = Methodref          #2.#53        // org/jetbrains/kotlin/android/synthetic/AndroidConstKt.getJavaIdentifierNameForResourceName:(Ljava/lang/String;)Ljava/lang/String;
+   #55 = Utf8               length
+   #56 = Utf8               ()I
+   #57 = NameAndType        #55:#56       // length:()I
+   #58 = InterfaceMethodref #28.#57       // java/lang/CharSequence.length:()I
    #59 = Utf8               <init>
    #60 = Utf8               (Ljava/lang/String;Ljava/lang/String;)V
    #61 = NameAndType        #59:#60       // "<init>":(Ljava/lang/String;Ljava/lang/String;)V
-   #62 = Methodref          #58.#61       // org/jetbrains/kotlin/android/synthetic/res/ResourceIdentifier."<init>":(Ljava/lang/String;Ljava/lang/String;)V
+   #62 = Methodref          #50.#61       // org/jetbrains/kotlin/android/synthetic/res/ResourceIdentifier."<init>":(Ljava/lang/String;Ljava/lang/String;)V
    #63 = Utf8               packageName
    #64 = Utf8               Ljava/lang/String;
    #65 = Utf8               values
    #66 = Utf8               Ljava/util/List;
    #67 = Utf8               styleName
@@ -75,11 +75,11 @@
    #69 = Utf8               java/lang/StringBuilder
    #70 = Class              #69           // java/lang/StringBuilder
    #71 = Utf8               ()V
    #72 = NameAndType        #59:#71       // "<init>":()V
    #73 = Methodref          #70.#72       // java/lang/StringBuilder."<init>":()V
-   #74 = Methodref          #48.#55       // java/lang/String.length:()I
+   #74 = Methodref          #48.#57       // java/lang/String.length:()I
    #75 = Utf8               charAt
    #76 = Utf8               (I)C
    #77 = NameAndType        #75:#76       // charAt:(I)C
    #78 = Methodref          #48.#77       // java/lang/String.charAt:(I)C
    #79 = Utf8               append
@@ -165,13 +165,13 @@
   #159 = Utf8               lastIndex
   #160 = Utf8               Lkotlin/jvm/functions/Function1;
   #161 = Utf8               Lkotlin/Metadata;
   #162 = Utf8               mv
   #163 = Integer            1
-  #164 = Integer            17
-  #165 = Utf8               bv
-  #166 = Integer            0
+  #164 = Integer            4
+  #165 = Integer            0
+  #166 = Utf8               bv
   #167 = Integer            3
   #168 = Utf8               k
   #169 = Integer            2
   #170 = Utf8               xi
   #171 = Utf8               d1
@@ -196,11 +196,11 @@
 {
   public static final org.jetbrains.kotlin.android.synthetic.res.ResourceIdentifier androidIdToName(java.lang.String);
     descriptor: (Ljava/lang/String;)Lorg/jetbrains/kotlin/android/synthetic/res/ResourceIdentifier;
     flags: ACC_PUBLIC, ACC_STATIC, ACC_FINAL
     Code:
-      stack=4, locals=11, args_size=1
+      stack=4, locals=5, args_size=1
          0: aload_0
          1: ldc           #10                 // String id
          3: invokestatic  #16                 // Method kotlin/jvm/internal/Intrinsics.checkNotNullParameter:(Ljava/lang/Object;Ljava/lang/String;)V
          6: getstatic     #22                 // Field org/jetbrains/kotlin/android/synthetic/AndroidConst.INSTANCE:Lorg/jetbrains/kotlin/android/synthetic/AndroidConst;
          9: invokevirtual #26                 // Method org/jetbrains/kotlin/android/synthetic/AndroidConst.getIDENTIFIER_REGEX:()Lkotlin/text/Regex;
@@ -220,75 +220,69 @@
         39: aload_1
         40: iconst_3
         41: invokeinterface #46,  2           // InterfaceMethod java/util/List.get:(I)Ljava/lang/Object;
         46: checkcast     #48                 // class java/lang/String
         49: astore_2
-        50: aload_1
-        51: iconst_4
-        52: invokeinterface #46,  2           // InterfaceMethod java/util/List.get:(I)Ljava/lang/Object;
-        57: checkcast     #48                 // class java/lang/String
-        60: invokestatic  #52                 // Method getJavaIdentifierNameForResourceName:(Ljava/lang/String;)Ljava/lang/String;
-        63: aload_2
-        64: checkcast     #28                 // class java/lang/CharSequence
-        67: astore_3
-        68: astore        7
-        70: iconst_0
-        71: istore        4
-        73: aload_3
-        74: invokeinterface #56,  1           // InterfaceMethod java/lang/CharSequence.length:()I
-        79: ifne          86
-        82: iconst_1
-        83: goto          87
-        86: iconst_0
-        87: istore        8
-        89: aload         7
-        91: iload         8
-        93: ifeq          100
-        96: aconst_null
-        97: goto          101
-       100: aload_2
-       101: astore        9
-       103: astore        10
-       105: new           #58                 // class org/jetbrains/kotlin/android/synthetic/res/ResourceIdentifier
-       108: dup
-       109: aload         10
-       111: aload         9
-       113: invokespecial #62                 // Method org/jetbrains/kotlin/android/synthetic/res/ResourceIdentifier."<init>":(Ljava/lang/String;Ljava/lang/String;)V
-       116: areturn
+        50: new           #50                 // class org/jetbrains/kotlin/android/synthetic/res/ResourceIdentifier
+        53: dup
+        54: aload_1
+        55: iconst_4
+        56: invokeinterface #46,  2           // InterfaceMethod java/util/List.get:(I)Ljava/lang/Object;
+        61: checkcast     #48                 // class java/lang/String
+        64: invokestatic  #54                 // Method getJavaIdentifierNameForResourceName:(Ljava/lang/String;)Ljava/lang/String;
+        67: aload_2
+        68: checkcast     #28                 // class java/lang/CharSequence
+        71: astore_3
+        72: iconst_0
+        73: istore        4
+        75: aload_3
+        76: invokeinterface #58,  1           // InterfaceMethod java/lang/CharSequence.length:()I
+        81: ifne          88
+        84: iconst_1
+        85: goto          89
+        88: iconst_0
+        89: ifeq          96
+        92: aconst_null
+        93: goto          97
+        96: aload_2
+        97: invokespecial #62                 // Method org/jetbrains/kotlin/android/synthetic/res/ResourceIdentifier."<init>":(Ljava/lang/String;Ljava/lang/String;)V
+       100: areturn
       StackMapTable: number_of_entries = 6
         frame_type = 99 /* same_locals_1_stack_item */
           stack = [ class java/lang/Object ]
         frame_type = 66 /* same_locals_1_stack_item */
           stack = [ class java/util/List ]
         frame_type = 255 /* full_frame */
-          offset_delta = 47
-          locals = [ class java/lang/String, class java/util/List, class java/lang/String, class java/lang/CharSequence, int, top, top, class java/lang/String ]
-          stack = []
-        frame_type = 64 /* same_locals_1_stack_item */
-          stack = [ int ]
+          offset_delta = 49
+          locals = [ class java/lang/String, class java/util/List, class java/lang/String, class java/lang/CharSequence, int ]
+          stack = [ uninitialized 50, uninitialized 50, class java/lang/String ]
         frame_type = 255 /* full_frame */
-          offset_delta = 12
-          locals = [ class java/lang/String, class java/util/List, class java/lang/String, class java/lang/CharSequence, int, top, top, class java/lang/String, int ]
-          stack = [ class java/lang/String ]
+          offset_delta = 0
+          locals = [ class java/lang/String, class java/util/List, class java/lang/String, class java/lang/CharSequence, int ]
+          stack = [ uninitialized 50, uninitialized 50, class java/lang/String, int ]
         frame_type = 255 /* full_frame */
+          offset_delta = 6
+          locals = [ class java/lang/String, class java/util/List, class java/lang/String, class java/lang/CharSequence, int ]
+          stack = [ uninitialized 50, uninitialized 50, class java/lang/String ]
+        frame_type = 255 /* full_frame */
           offset_delta = 0
-          locals = [ class java/lang/String, class java/util/List, class java/lang/String, class java/lang/CharSequence, int, top, top, class java/lang/String, int ]
-          stack = [ class java/lang/String, class java/lang/String ]
+          locals = [ class java/lang/String, class java/util/List, class java/lang/String, class java/lang/CharSequence, int ]
+          stack = [ uninitialized 50, uninitialized 50, class java/lang/String, class java/lang/String ]
       LineNumberTable:
         line 61: 6
         line 61: 35
         line 62: 39
         line 64: 50
-        line 65: 50
-        line 66: 63
-        line 66: 96
-        line 64: 101
+        line 65: 54
+        line 66: 67
+        line 66: 89
+        line 64: 97
       LocalVariableTable:
         Start  Length  Slot  Name   Signature
-           50      67     2 packageName   Ljava/lang/String;
-           39      78     1 values   Ljava/util/List;
-            0     117     0    id   Ljava/lang/String;
+           50      51     2 packageName   Ljava/lang/String;
+           39      62     1 values   Ljava/util/List;
+            0     101     0    id   Ljava/lang/String;
     RuntimeInvisibleAnnotations:
       0: #7()
     RuntimeInvisibleParameterAnnotations:
       0:
         0: #8()
@@ -366,11 +360,13 @@
         frame_type = 7 /* same */
         frame_type = 250 /* chop */
           offset_delta = 5
       LineNumberTable:
         line 71: 6
+        line 65100: 24
         line 72: 27
+        line 72: 40
         line 73: 56
         line 74: 92
         line 75: 103
         line 76: 111
         line 72: 111
@@ -378,12 +374,12 @@
         line 71: 118
         line 78: 128
       LocalVariableTable:
         Start  Length  Slot  Name   Signature
            56      58    10  char   C
-           24      93     5 $this$buildString   Ljava/lang/StringBuilder;
-           27      90     6 $i$a$-buildString-AndroidConstKt$getJavaIdentifierNameForResourceName$1   I
+           24      94     5 $this$buildString   Ljava/lang/StringBuilder;
+           27      91     6 $i$a$-buildString-AndroidConstKt$getJavaIdentifierNameForResourceName$1   I
             0     129     0 styleName   Ljava/lang/String;
     RuntimeInvisibleAnnotations:
       0: #8()
     RuntimeInvisibleParameterAnnotations:
       0:
@@ -401,11 +397,11 @@
          7: checkcast     #28                 // class java/lang/CharSequence
         10: astore_1
         11: iconst_0
         12: istore_2
         13: aload_1
-        14: invokeinterface #56,  1           // InterfaceMethod java/lang/CharSequence.length:()I
+        14: invokeinterface #58,  1           // InterfaceMethod java/lang/CharSequence.length:()I
         19: ifne          26
         22: iconst_1
         23: goto          27
         26: iconst_0
         27: ifne          45
@@ -552,17 +548,17 @@
   org/jetbrains/kotlin/android/synthetic/AndroidConstKt
   + 2 _Collections.kt
   kotlin/collections/CollectionsKt___CollectionsKt
   *L
   1#1,92:1
-  1653#2,3:93
+  1651#2,3:93
   *E
   *S KotlinDebug
   *F
   + 1 AndroidConst.kt
   org/jetbrains/kotlin/android/synthetic/AndroidConstKt
   *L
   86#1,3:93
   *E
 RuntimeVisibleAnnotations:
-  0: #161(#162=[I#163,I#163,I#164],#165=[I#163,I#166,I#167],#168=I#169,#170=I#169,#171=[s#172],#173=[s#5,s#174,s#9,s#175,s#49,s#67,s#98,s#175,s#100,s#112,s#175,s#176,s#175,s#117,s#177,s#178])
+  0: #161(#162=[I#163,I#164,I#165],#166=[I#163,I#165,I#167],#168=I#169,#170=I#169,#171=[s#172],#173=[s#5,s#174,s#9,s#175,s#51,s#67,s#98,s#175,s#100,s#112,s#175,s#176,s#175,s#117,s#177,s#178])
 
